hwo_custom_markers/__init__.py
hwo_custom_markers/generate_custom_markers.py
hwo_custom_markers/support_data/cds_pupil_monolithic_128.svg
hwo_custom_markers/support_data/cds_pupil_offaxis_128.svg
hwo_custom_markers/support_data/cds_pupil_onaxis_128.svg
hwo_custom_markers/support_data/luvoir_a_gaps_1024.svg
hwo_custom_markers/support_data/luvoir_a_nogaps_1024.svg
hwo_custom_markers/support_data/luvoir_b_gaps_1024.svg
hwo_custom_markers/support_data/luvoir_b_nogaps_1024.svg
hwo_custom_markers/support_data/demo_images/available_markers.png
hwo_custom_markers-1.2.dist-info/METADATA
hwo_custom_markers-1.2.dist-info/WHEEL
hwo_custom_markers-1.2.dist-info/top_level.txt
hwo_custom_markers-1.2.dist-info/RECORD
